pynautical/__init__.py
pynautical/course.py
pynautical/distance.py
pynautical/route.py
pynautical/units.py
pynautical/version.py
pynautical-0.1.dist-info/licenses/LICENSE
pynautical-0.1.dist-info/METADATA
pynautical-0.1.dist-info/WHEEL
pynautical-0.1.dist-info/top_level.txt
pynautical-0.1.dist-info/RECORD
