Metadata-Version: 2.4
Name: PyNautical
Version: 0.1
Summary: A nautical library for calculations in Python.
Home-page: https://github.com/s-w-chen/pynautical
Author: Sheng-Wen,Chen
Author-email: dannis.sw.chen@gmail.com
License: MIT
Project-URL: Homepage, https://github.com/s-w-chen/pynautical
Project-URL: Source, https://github.com/s-w-chen/pynautical
Project-URL: Documentation, https://github.com/s-w-chen/pynautical#readme
Keywords: nautical,navigation,geodesy,marine,coordinates,distance,course,bearing,rhumbline,great circle,WGS84,python
Classifier: Development Status :: 3 - Alpha
Classifier: Intended Audience :: Developers
Classifier: Intended Audience :: Education
Classifier: Intended Audience :: Other Audience
Classifier: Intended Audience :: Science/Research
Classifier: License :: OSI Approved :: MIT License
Classifier: Operating System :: OS Independent
Classifier: Programming Language :: Python
Classifier: Programming Language :: Python :: 3
Classifier: Programming Language :: Python :: 3.9
Classifier: Programming Language :: Python :: 3.10
Classifier: Programming Language :: Python :: 3.11
Classifier: Programming Language :: Python :: 3.12
Classifier: Programming Language :: Python :: 3.13
Classifier: Topic :: Software Development :: Libraries
Classifier: Topic :: Software Development :: Libraries :: Python Modules
Requires-Python: >=3.9
License-File: LICENSE
Dynamic: author
Dynamic: author-email
Dynamic: classifier
Dynamic: description
Dynamic: description-content-type
Dynamic: home-page
Dynamic: keywords
Dynamic: license
Dynamic: license-file
Dynamic: project-url
Dynamic: requires-python
Dynamic: summary
